cocoder/__init__.py
cocoder/chatbase/__init__.py
cocoder/chatbase/bard_receiver.py
cocoder/chatbase/openai_receiver.py
cocoder/ipython/__init__.py
cocoder/ipython/core.py
cocoder/python/__init__.py
cocoder/python/core.py
cocoder-0.1.5.dist-info/LICENSE
cocoder-0.1.5.dist-info/METADATA
cocoder-0.1.5.dist-info/WHEEL
cocoder-0.1.5.dist-info/entry_points.txt
cocoder-0.1.5.dist-info/top_level.txt
cocoder-0.1.5.dist-info/RECORD
