Metadata-Version: 2.1
Name: cocoder
Version: 0.1.5
Home-page: https://github.com/dsdanielpark/Co-Coder
Author: daniel park
Author-email: parkminwoo1991@gmail.com
Keywords: Python Debuger,Python AI Debug,Realtime Debuger,Search,Find Debug Infomation,Bard,ChatGPT,GoogleBard,OpenAIchatGPT
Classifier: Development Status :: 2 - Pre-Alpha
Classifier: Intended Audience :: Science/Research
Classifier: Natural Language :: English
Classifier: Programming Language :: Python
Classifier: Programming Language :: Python :: 3.6
Classifier: Programming Language :: Python :: 3.7
Classifier: Programming Language :: Python :: 3.8
Classifier: License :: OSI Approved :: MIT License
Classifier: Programming Language :: Python :: 3.6
Classifier: Topic :: Scientific/Engineering :: Artificial Intelligence
Requires-Python: >=3.6
License-File: LICENSE
Requires-Dist: openai
Requires-Dist: bardapi
